llama_index/protocols/ag_ui/__init__.py
llama_index/protocols/ag_ui/agent.py
llama_index/protocols/ag_ui/events.py
llama_index/protocols/ag_ui/router.py
llama_index/protocols/ag_ui/utils.py
llama_index_protocols_ag_ui-0.2.2.dist-info/METADATA
llama_index_protocols_ag_ui-0.2.2.dist-info/WHEEL
llama_index_protocols_ag_ui-0.2.2.dist-info/licenses/LICENSE
llama_index_protocols_ag_ui-0.2.2.dist-info/RECORD
