Metadata-Version: 2.4
Name: llama-index-protocols-ag-ui
Version: 0.2.2
Summary: llama-index protocols AG-UI integration
Author-email: Logan Markewich <logan@runllama.ai>
License-Expression: MIT
License-File: LICENSE
Requires-Python: <3.14,>=3.9
Requires-Dist: ag-ui-protocol>=0.1.5
Requires-Dist: llama-index-core<0.15,>=0.13.0
Provides-Extra: fastapi
Requires-Dist: fastapi; extra == 'fastapi'
